{
  "eu": {
    "code": "eu",
    "name": "EU",
    "gasDayStart": "2026-04-17",
    "gasInStorageTWh": 338.85,
    "workingGasVolumeTWh": 1132.23,
    "fullPct": 29.93,
    "injectionGWhPerDay": 2856.84,
    "withdrawalGWhPerDay": 306.6,
    "netWithdrawalGWhPerDay": -2550.3,
    "status": "E"
  },
  "countries": [
    {
      "code": "DE",
      "name": "Germany",
      "gasDayStart": "2026-04-17",
      "gasInStorageTWh": 57.61,
      "workingGasVolumeTWh": 247.9,
      "fullPct": 23.24,
      "injectionGWhPerDay": 472.66,
      "withdrawalGWhPerDay": 22.5,
      "netWithdrawalGWhPerDay": -450.2,
      "status": "E",
      "dayOverDayFullPctChange": 0.18
    },
    {
      "code": "IT",
      "name": "Italy",
      "gasDayStart": "2026-04-17",
      "gasInStorageTWh": 92.93,
      "workingGasVolumeTWh": 203.84,
      "fullPct": 45.59,
      "injectionGWhPerDay": 660.55,
      "withdrawalGWhPerDay": 0,
      "netWithdrawalGWhPerDay": -660.5,
      "status": "C",
      "dayOverDayFullPctChange": 0.33
    },
    {
      "code": "FR",
      "name": "France",
      "gasDayStart": "2026-04-17",
      "gasInStorageTWh": 33.52,
      "workingGasVolumeTWh": 123.88,
      "fullPct": 27.06,
      "injectionGWhPerDay": 583.09,
      "withdrawalGWhPerDay": 42.9,
      "netWithdrawalGWhPerDay": -540.2,
      "status": "C",
      "dayOverDayFullPctChange": 0.43
    },
    {
      "code": "NL",
      "name": "Netherlands",
      "gasDayStart": "2026-04-17",
      "gasInStorageTWh": 10.26,
      "workingGasVolumeTWh": 143.79,
      "fullPct": 7.13,
      "injectionGWhPerDay": 409.46,
      "withdrawalGWhPerDay": 37.6,
      "netWithdrawalGWhPerDay": -371.8,
      "status": "C",
      "dayOverDayFullPctChange": 0.26
    },
    {
      "code": "AT",
      "name": "Austria",
      "gasDayStart": "2026-04-17",
      "gasInStorageTWh": 35.97,
      "workingGasVolumeTWh": 100.28,
      "fullPct": 35.87,
      "injectionGWhPerDay": 196.33,
      "withdrawalGWhPerDay": 0,
      "netWithdrawalGWhPerDay": -196.3,
      "status": "C",
      "dayOverDayFullPctChange": 0.2
    },
    {
      "code": "BE",
      "name": "Belgium",
      "gasDayStart": "2026-04-17",
      "gasInStorageTWh": 1.81,
      "workingGasVolumeTWh": 7.61,
      "fullPct": 23.77,
      "injectionGWhPerDay": 19.48,
      "withdrawalGWhPerDay": 0,
      "netWithdrawalGWhPerDay": -19.5,
      "status": "C",
      "dayOverDayFullPctChange": 0.25
    },
    {
      "code": "CZ",
      "name": "Czech Republic",
      "gasDayStart": "2026-04-17",
      "gasInStorageTWh": 12.77,
      "workingGasVolumeTWh": 45.3,
      "fullPct": 28.19,
      "injectionGWhPerDay": 57.61,
      "withdrawalGWhPerDay": 89.7,
      "netWithdrawalGWhPerDay": 32.1,
      "status": "C",
      "dayOverDayFullPctChange": -0.07
    },
    {
      "code": "DK",
      "name": "Denmark",
      "gasDayStart": "2026-04-17",
      "gasInStorageTWh": 3.32,
      "workingGasVolumeTWh": 8.59,
      "fullPct": 38.6,
      "injectionGWhPerDay": 20.1,
      "withdrawalGWhPerDay": 3.8,
      "netWithdrawalGWhPerDay": -16.3,
      "status": "C",
      "dayOverDayFullPctChange": 0.19
    },
    {
      "code": "ES",
      "name": "Spain",
      "gasDayStart": "2026-04-17",
      "gasInStorageTWh": 22.61,
      "workingGasVolumeTWh": 35.83,
      "fullPct": 63.09,
      "injectionGWhPerDay": 114.88,
      "withdrawalGWhPerDay": 0,
      "netWithdrawalGWhPerDay": -114.9,
      "status": "E",
      "dayOverDayFullPctChange": 0.32
    },
    {
      "code": "HR",
      "name": "Croatia",
      "gasDayStart": "2026-04-17",
      "gasInStorageTWh": 0.84,
      "workingGasVolumeTWh": 4.77,
      "fullPct": 17.61,
      "injectionGWhPerDay": 22.87,
      "withdrawalGWhPerDay": 0.2,
      "netWithdrawalGWhPerDay": -22.6,
      "status": "C",
      "dayOverDayFullPctChange": 0.48
    },
    {
      "code": "HU",
      "name": "Hungary",
      "gasDayStart": "2026-04-17",
      "gasInStorageTWh": 22.89,
      "workingGasVolumeTWh": 67.99,
      "fullPct": 33.67,
      "injectionGWhPerDay": 111.13,
      "withdrawalGWhPerDay": 0,
      "netWithdrawalGWhPerDay": -111.1,
      "status": "C",
      "dayOverDayFullPctChange": 0.16
    },
    {
      "code": "LV",
      "name": "Latvia",
      "gasDayStart": "2026-04-17",
      "gasInStorageTWh": 6.32,
      "workingGasVolumeTWh": 24.87,
      "fullPct": 25.42,
      "injectionGWhPerDay": 0,
      "withdrawalGWhPerDay": 16.1,
      "netWithdrawalGWhPerDay": 16.1,
      "status": "C",
      "dayOverDayFullPctChange": -0.07
    },
    {
      "code": "PL",
      "name": "Poland",
      "gasDayStart": "2026-04-17",
      "gasInStorageTWh": 15.86,
      "workingGasVolumeTWh": 36.31,
      "fullPct": 43.69,
      "injectionGWhPerDay": 42.98,
      "withdrawalGWhPerDay": 0,
      "netWithdrawalGWhPerDay": -43,
      "status": "C",
      "dayOverDayFullPctChange": 0.75
    },
    {
      "code": "PT",
      "name": "Portugal",
      "gasDayStart": "2026-04-17",
      "gasInStorageTWh": 3.24,
      "workingGasVolumeTWh": 3.57,
      "fullPct": 90.72,
      "injectionGWhPerDay": 0,
      "withdrawalGWhPerDay": 31.6,
      "netWithdrawalGWhPerDay": 31.6,
      "status": "C",
      "dayOverDayFullPctChange": -0.89
    },
    {
      "code": "RO",
      "name": "Romania",
      "gasDayStart": "2026-04-17",
      "gasInStorageTWh": 8.51,
      "workingGasVolumeTWh": 33.86,
      "fullPct": 25.13,
      "injectionGWhPerDay": 91.56,
      "withdrawalGWhPerDay": 0.1,
      "netWithdrawalGWhPerDay": -91.5,
      "status": "C",
      "dayOverDayFullPctChange": 0.27
    },
    {
      "code": "SE",
      "name": "Sweden",
      "gasDayStart": "2026-04-17",
      "gasInStorageTWh": 0.01,
      "workingGasVolumeTWh": 0.08,
      "fullPct": 9.92,
      "injectionGWhPerDay": 0,
      "withdrawalGWhPerDay": 0,
      "netWithdrawalGWhPerDay": 0,
      "status": "C",
      "dayOverDayFullPctChange": 0
    },
    {
      "code": "SK",
      "name": "Slovakia",
      "gasDayStart": "2026-04-17",
      "gasInStorageTWh": 8.47,
      "workingGasVolumeTWh": 36.74,
      "fullPct": 23.06,
      "injectionGWhPerDay": 54.15,
      "withdrawalGWhPerDay": 35.1,
      "netWithdrawalGWhPerDay": -19.1,
      "status": "C",
      "dayOverDayFullPctChange": 0.05
    }
  ]
}
